package/__init__.py
package/main.py
trxone-0.0.1.dist-info/licenses/LICENSE.txt
trxone-0.0.1.dist-info/METADATA
trxone-0.0.1.dist-info/WHEEL
trxone-0.0.1.dist-info/top_level.txt
trxone-0.0.1.dist-info/RECORD
