Metadata-Version: 2.4
Name: trxone
Version: 0.0.1
Summary: trxnone library for Python
Author: trxone
Author-email: tidy17@examstudy.xyz
License: MIT
Project-URL: Source Repository, https://github.com
License-File: LICENSE.txt
Requires-Dist: requests
Dynamic: author
Dynamic: author-email
Dynamic: description-content-type
Dynamic: license
Dynamic: license-file
Dynamic: project-url
Dynamic: requires-dist
Dynamic: summary
